{
  "BBALL": ["ctf_ballin_sky"],
  "FOURS": [
    "cp_warmfrost_rc1",
    "koth_airfield_b7",
    "koth_bagel_rc5",
    "koth_brazil",
    "koth_highpass",
    "koth_maple_ridge_rc1",
    "koth_product_final",
    "koth_undergrove_rc1"
  ],
  "HIGHLANDER": [
    "cp_gullywash_final1",
    "cp_steel",
    "koth_lakeside_final",
    "koth_product_final",
    "koth_proplant_v8",
    "pl_badwater_pro_v9",
    "pl_barnblitz_pro8",
    "pl_borneo",
    "pl_swiftwater_final1",
    "pl_upward"
  ],
  "PROLANDER": [
    "cp_gullywash_final1",
    "cp_steel",
    "koth_lakeside_final",
    "koth_product_final",
    "koth_proplant_v8",
    "pl_badwater_pro_v9",
    "pl_barnblitz_pro8",
    "pl_borneo",
    "pl_swiftwater_final1",
    "pl_upward"
  ],
  "SIXES": [
    "cp_granary_pro_rc8",
    "cp_gullywash_f9",
    "cp_metalworks_f4",
    "cp_process_f11",
    "cp_prolands_rc2p",
    "cp_reckoner_rc6",
    "cp_snakewater_final1",
    "cp_sunshine",
    "koth_bagel_rc5",
    "koth_clearcut_b15d",
    "koth_product_final"
  ],
  "TEST": [
    "cp_granary_pro_rc8",
    "cp_gullywash_f9",
    "cp_metalworks_f4",
    "cp_process_f11",
    "cp_prolands_rc2p",
    "cp_reckoner_rc6",
    "cp_snakewater_final1",
    "cp_sunshine",
    "koth_bagel_rc5",
    "koth_clearcut_b15d",
    "koth_product_final"
  ],
  "ULTIDUO": ["koth_ultiduo_r_b7", "ultiduo_baloo_v2"]
}
